state_machine/__init__.py
state_machine/errors.py
state_machine/machine.py
Fusion_State_Machine-0.1.4.dist-info/LICENSE
Fusion_State_Machine-0.1.4.dist-info/METADATA
Fusion_State_Machine-0.1.4.dist-info/WHEEL
Fusion_State_Machine-0.1.4.dist-info/top_level.txt
Fusion_State_Machine-0.1.4.dist-info/RECORD
