Metadata-Version: 2.1
Name: Fusion-State-Machine
Version: 0.1.4
Summary: Utility to turn your class into a state machine
Author-email: Jisus17 <cjisus4@gmail.com>
License: MIT License
Project-URL: Homepage, https://github.com/Jisus17/Fusion-State-Machine/
Keywords: state-machine,states-machine-controller,machine-state-controller,machine-state
Classifier: Development Status :: 5 - Production/Stable
Classifier: Intended Audience :: Developers
Classifier: Topic :: Software Development :: Build Tools
Classifier: License :: OSI Approved :: GNU General Public License (GPL)
Classifier: Programming Language :: Python :: 3.8
Classifier: Programming Language :: Python :: 3.9
Classifier: Programming Language :: Python :: 3.10
Classifier: Programming Language :: Python :: 3.11
Requires-Python: >=3.8
License-File: LICENSE
Provides-Extra: dev
